Workbook

Sheet BvA_Report
B1: NovaPay: Budget vs. Actual, Jan–Jun 2024 (fictional company)
A2: Month | B2: Month | C2: Month_Number | D2: Actual Revenue | E2: Budget Revenue | F2: Variance | G2: Var % | H2: Actual Opex | I2: Budget Opex | J2: Variance | K2: Var % | L2: Actual EBITDA | M2: Budget EBITDA | N2: Variance | O2: Var %
A3: 45292 | B3: =TEXT(A3,"mmm-yy") -> Jan-24 | C3: =MONTH(A3) -> 1 | D3: =_xlfn.XLOOKUP(A3,Monthly_Summary!A:A,Monthly_Summary!D:D) -> 4187 | E3: =_xlfn.XLOOKUP(A3,tblBudget[Month],tblBudget[Budget_Total_Revenue]) -> 4200 | F3: =D3-E3 -> -13 | G3: =F3/E3 -> -0.0030952381 | H3: =_xlfn.XLOOKUP(A3,Monthly_Summary!A:A,Monthly_Summary!E:E) -> 37850 | I3: =_xlfn.XLOOKUP(A3,tblBudget[Month],tblBudget[Budget_Operating_Expenses]) -> 36000 | J3: =H3-I3 -> 1850 | K3: =J3/I3 -> 0.051388889 | L3: =_xlfn.XLOOKUP(A3,Monthly_Summary!A:A,Monthly_Summary!I:I) -> -34960.97 | M3: =_xlfn.XLOOKUP(A3,tblBudget[Month],tblBudget[Budget_EBITDA]) -> -33100 | N3: =L3-M3 -> -1860.97 | O3: =N3/ABS(M3) -> -0.056222659
A4: 45323 | B4: =TEXT(A4,"mmm-yy") -> Feb-24 | C4: =MONTH(A4) -> 2 | D4: =_xlfn.XLOOKUP(A4,Monthly_Summary!A:A,Monthly_Summary!D:D) -> 3052 | E4: =_xlfn.XLOOKUP(A4,tblBudget[Month],tblBudget[Budget_Total_Revenue]) -> 3100 | F4: =D4-E4 -> -48 | G4: =F4/E4 -> -0.015483871 | H4: =_xlfn.XLOOKUP(A4,Monthly_Summary!A:A,Monthly_Summary!E:E) -> 38000 | I4: =_xlfn.XLOOKUP(A4,tblBudget[Month],tblBudget[Budget_Operating_Expenses]) -> 36700 | J4: =H4-I4 -> 1300 | K4: =J4/I4 -> 0.035422343 | L4: =_xlfn.XLOOKUP(A4,Monthly_Summary!A:A,Monthly_Summary!I:I) -> -35924.64 | M4: =_xlfn.XLOOKUP(A4,tblBudget[Month],tblBudget[Budget_EBITDA]) -> -34950 | N4: =L4-M4 -> -974.64 | O4: =N4/ABS(M4) -> -0.027886695
A5: 45352 | B5: =TEXT(A5,"mmm-yy") -> Mar-24 | C5: =MONTH(A5) -> 3 | D5: =_xlfn.XLOOKUP(A5,Monthly_Summary!A:A,Monthly_Summary!D:D) -> 4358 | E5: =_xlfn.XLOOKUP(A5,tblBudget[Month],tblBudget[Budget_Total_Revenue]) -> 4250 | F5: =D5-E5 -> 108 | G5: =F5/E5 -> 0.025411765 | H5: =_xlfn.XLOOKUP(A5,Monthly_Summary!A:A,Monthly_Summary!E:E) -> 39250 | I5: =_xlfn.XLOOKUP(A5,tblBudget[Month],tblBudget[Budget_Operating_Expenses]) -> 38300 | J5: =H5-I5 -> 950 | K5: =J5/I5 -> 0.024804178 | L5: =_xlfn.XLOOKUP(A5,Monthly_Summary!A:A,Monthly_Summary!I:I) -> -36373.72 | M5: =_xlfn.XLOOKUP(A5,tblBudget[Month],tblBudget[Budget_EBITDA]) -> -35550 | N5: =L5-M5 -> -823.72 | O5: =N5/ABS(M5) -> -0.023170745
A6: 45383 | B6: =TEXT(A6,"mmm-yy") -> Apr-24 | C6: =MONTH(A6) -> 4 | D6: =_xlfn.XLOOKUP(A6,Monthly_Summary!A:A,Monthly_Summary!D:D) -> 6583 | E6: =_xlfn.XLOOKUP(A6,tblBudget[Month],tblBudget[Budget_Total_Revenue]) -> 5400 | F6: =D6-E6 -> 1183 | G6: =F6/E6 -> 0.21907407 | H6: =_xlfn.XLOOKUP(A6,Monthly_Summary!A:A,Monthly_Summary!E:E) -> 41550 | I6: =_xlfn.XLOOKUP(A6,tblBudget[Month],tblBudget[Budget_Operating_Expenses]) -> 40200 | J6: =H6-I6 -> 1350 | K6: =J6/I6 -> 0.03358209 | L6: =_xlfn.XLOOKUP(A6,Monthly_Summary!A:A,Monthly_Summary!I:I) -> -37271.05 | M6: =_xlfn.XLOOKUP(A6,tblBudget[Month],tblBudget[Budget_EBITDA]) -> -36550 | N6: =L6-M6 -> -721.05 | O6: =N6/ABS(M6) -> -0.01972777
A7: 45413 | B7: =TEXT(A7,"mmm-yy") -> May-24 | C7: =MONTH(A7) -> 5 | D7: =_xlfn.XLOOKUP(A7,Monthly_Summary!A:A,Monthly_Summary!D:D) -> 7280 | E7: =_xlfn.XLOOKUP(A7,tblBudget[Month],tblBudget[Budget_Total_Revenue]) -> 5950 | F7: =D7-E7 -> 1330 | G7: =F7/E7 -> 0.22352941 | H7: =_xlfn.XLOOKUP(A7,Monthly_Summary!A:A,Monthly_Summary!E:E) -> 44600 | I7: =_xlfn.XLOOKUP(A7,tblBudget[Month],tblBudget[Budget_Operating_Expenses]) -> 41500 | J7: =H7-I7 -> 3100 | K7: =J7/I7 -> 0.074698795 | L7: =_xlfn.XLOOKUP(A7,Monthly_Summary!A:A,Monthly_Summary!I:I) -> -39940.8 | M7: =_xlfn.XLOOKUP(A7,tblBudget[Month],tblBudget[Budget_EBITDA]) -> -37500 | N7: =L7-M7 -> -2440.8 | O7: =N7/ABS(M7) -> -0.065088
A8: 45444 | B8: =TEXT(A8,"mmm-yy") -> Jun-24 | C8: =MONTH(A8) -> 6 | D8: =_xlfn.XLOOKUP(A8,Monthly_Summary!A:A,Monthly_Summary!D:D) -> 9531 | E8: =_xlfn.XLOOKUP(A8,tblBudget[Month],tblBudget[Budget_Total_Revenue]) -> 7000 | F8: =D8-E8 -> 2531 | G8: =F8/E8 -> 0.36157143 | H8: =_xlfn.XLOOKUP(A8,Monthly_Summary!A:A,Monthly_Summary!E:E) -> 43750 | I8: =_xlfn.XLOOKUP(A8,tblBudget[Month],tblBudget[Budget_Operating_Expenses]) -> 42100 | J8: =H8-I8 -> 1650 | K8: =J8/I8 -> 0.039192399 | L8: =_xlfn.XLOOKUP(A8,Monthly_Summary!A:A,Monthly_Summary!I:I) -> -37745.47 | M8: =_xlfn.XLOOKUP(A8,tblBudget[Month],tblBudget[Budget_EBITDA]) -> -37300 | N8: =L8-M8 -> -445.47 | O8: =N8/ABS(M8) -> -0.011942895
B9: TOTAL | D9: =SUM(D3:D8) -> 34991 | E9: =SUM(E3:E8) -> 29900 | F9: =SUM(F3:F8) -> 5091 | G9: =F9/E9 -> 0.17026756 | H9: =SUM(H3:H8) -> 245000 | I9: =SUM(I3:I8) -> 234800 | J9: =SUM(J3:J8) -> 10200 | K9: =J9/I9 -> 0.043441227 | L9: =SUM(L3:L8) -> -222216.65 | M9: =SUM(M3:M8) -> -214950 | N9: =SUM(N3:N8) -> -7266.65 | O9: =N9/ABS(M9) -> -0.033806234

Sheet README
D2: NovaPay FP&A Model Purpose: This Excel model analyzes monthly revenue, expenses, budget vs actual performance, EBITDA, churn, CAC, and scenario planning for a fictional fintech subscription business. Data Sources: Revenue_Data Expense_Data Budget_Data KPI_Data Scenario_Inputs Main Outputs: Monthly Summary Budget vs Actual Analysis P&L Model Scenario Analysis CFO Summary

Sheet Revenue_Data
A1: Month | B1: Month_Label | C1: Month_Number | D1: Customer_ID | E1: Subscription_Revenue | F1: Transaction_Volume | G1: Transaction_Fee_Revenue | H1: Premium_Analytics_Revenue | I1: Setup_Fee_Revenue | J1: Total_Revenue
A2: 45292 | B2: =TEXT(A2,"mmm-yy") -> Jan-24 | C2: =MONTH(A2) -> 1 | D2: C001 | E2: 299 | F2: 45000 | G2: 585 | H2: 0 | I2: 500 | J2: 1384
A3: 45323 | B3: =TEXT(A3,"mmm-yy") -> Feb-24 | C3: =MONTH(A3) -> 2 | D3: C001 | E3: 299 | F3: 47000 | G3: 611 | H3: 0 | I3: 0 | J3: 910
A4: 45352 | B4: =TEXT(A4,"mmm-yy") -> Mar-24 | C4: =MONTH(A4) -> 3 | D4: C001 | E4: 299 | F4: 51000 | G4: 663 | H4: 0 | I4: 0 | J4: 962
A5: 45383 | B5: =TEXT(A5,"mmm-yy") -> Apr-24 | C5: =MONTH(A5) -> 4 | D5: C001 | E5: 299 | F5: 53000 | G5: 689 | H5: 0 | I5: 0 | J5: 988
A6: 45413 | B6: =TEXT(A6,"mmm-yy") -> May-24 | C6: =MONTH(A6) -> 5 | D6: C001 | E6: 299 | F6: 56000 | G6: 728 | H6: 0 | I6: 0 | J6: 1027
A7: 45444 | B7: =TEXT(A7,"mmm-yy") -> Jun-24 | C7: =MONTH(A7) -> 6 | D7: C001 | E7: 299 | F7: 59000 | G7: 767 | H7: 0 | I7: 0 | J7: 1066
A8: 45292 | B8: =TEXT(A8,"mmm-yy") -> Jan-24 | C8: =MONTH(A8) -> 1 | D8: C002 | E8: 799 | F8: 85000 | G8: 1105 | H8: 199 | I8: 700 | J8: 2803
A9: 45323 | B9: =TEXT(A9,"mmm-yy") -> Feb-24 | C9: =MONTH(A9) -> 2 | D9: C002 | E9: 799 | F9: 88000 | G9: 1144 | H9: 199 | I9: 0 | J9: 2142
A10: 45352 | B10: =TEXT(A10,"mmm-yy") -> Mar-24 | C10: =MONTH(A10) -> 3 | D10: C002 | E10: 799 | F10: 91000 | G10: 1183 | H10: 199 | I10: 0 | J10: 2181
A11: 45383 | B11: =TEXT(A11,"mmm-yy") -> Apr-24 | C11: =MONTH(A11) -> 4 | D11: C002 | E11: 799 | F11: 94000 | G11: 1222 | H11: 199 | I11: 0 | J11: 2220
A12: 45413 | B12: =TEXT(A12,"mmm-yy") -> May-24 | C12: =MONTH(A12) -> 5 | D12: C002 | E12: 799 | F12: 97000 | G12: 1261 | H12: 199 | I12: 0 | J12: 2259
A13: 45444 | B13: =TEXT(A13,"mmm-yy") -> Jun-24 | C13: =MONTH(A13) -> 6 | D13: C002 | E13: 799 | F13: 102000 | G13: 1326 | H13: 199 | I13: 0 | J13: 2324
... A23: 45444 | B23: =TEXT(A23,"mmm-yy") -> Jun-24 | C23: =MONTH(A23) -> 6 | D23: C006 | E23: 799 | F23: 69000 | G23: 897 | H23: 199 | I23: 700 | J23: 2595

Sheet Customers
A1: Customer_ID | B1: Customer_Name
A2: C001 | B2: Acme Corp
A3: C002 | B3: TechStart Ltd
A4: C003 | B4: BluePeak Systems
A5: C004 | B5: Nova Retail Group
A6: C005 | B6: FinEdge Partners
A7: C006 | B7: CloudBridge Inc

Sheet Date_Table
A1: Month_Date | B1: Month_Label | C1: Month_Number | D1: Month_Year
A2: =DATE(2024,1,1) -> 45292 | B2: =TEXT(A2,"mmm-yy") -> Jan-24 | C2: =MONTH(A2) -> 1 | D2: =YEAR(A2)*100+MONTH(A2) -> 202401
A3: =EDATE(A2,1) -> 45323 | B3: =TEXT(A3,"mmm-yy") -> Feb-24 | C3: =MONTH(A3) -> 2 | D3: =YEAR(A3)*100+MONTH(A3) -> 202402
A4: =EDATE(A3,1) -> 45352 | B4: =TEXT(A4,"mmm-yy") -> Mar-24 | C4: =MONTH(A4) -> 3 | D4: =YEAR(A4)*100+MONTH(A4) -> 202403
A5: =EDATE(A4,1) -> 45383 | B5: =TEXT(A5,"mmm-yy") -> Apr-24 | C5: =MONTH(A5) -> 4 | D5: =YEAR(A5)*100+MONTH(A5) -> 202404
A6: =EDATE(A5,1) -> 45413 | B6: =TEXT(A6,"mmm-yy") -> May-24 | C6: =MONTH(A6) -> 5 | D6: =YEAR(A6)*100+MONTH(A6) -> 202405
A7: =EDATE(A6,1) -> 45444 | B7: =TEXT(A7,"mmm-yy") -> Jun-24 | C7: =MONTH(A7) -> 6 | D7: =YEAR(A7)*100+MONTH(A7) -> 202406

Sheet Expense_Data
A1: Month | B1: Month_Label | C1: Month_Number | D1: Department | E1: Expense_Category | F1: Budget_Expense | G1: Actual_Expense | H1: Vendor | I1: Cost_Type
A2: 45292 | B2: =TEXT(A2,"mmm-yy") -> Jan-24 | C2: =MONTH(A2) -> 1 | D2: Sales | E2: Payroll | F2: 12000 | G2: 12000 | H2: Internal Payroll | I2: Fixed
A3: 45292 | B3: =TEXT(A3,"mmm-yy") -> Jan-24 | C3: =MONTH(A3) -> 1 | D3: Marketing | E3: Marketing Spend | F3: 8000 | G3: 9200 | H3: Google Ads | I3: Variable
A4: 45292 | B4: =TEXT(A4,"mmm-yy") -> Jan-24 | C4: =MONTH(A4) -> 1 | D4: Product | E4: Cloud Hosting | F4: 4500 | G4: 5100 | H4: AWS | I4: Variable
A5: 45292 | B5: =TEXT(A5,"mmm-yy") -> Jan-24 | C5: =MONTH(A5) -> 1 | D5: Customer Support | E5: Customer Support Tools | F5: 2500 | G5: 2400 | H5: Zendesk | I5: Fixed
A6: 45292 | B6: =TEXT(A6,"mmm-yy") -> Jan-24 | C6: =MONTH(A6) -> 1 | D6: Operations | E6: Software | F6: 3000 | G6: 3150 | H6: Salesforce | I6: Fixed
A7: 45292 | B7: =TEXT(A7,"mmm-yy") -> Jan-24 | C7: =MONTH(A7) -> 1 | D7: G&A | E7: Rent | F7: 6000 | G7: 6000 | H7: WeWork | I7: Fixed
A8: 45323 | B8: =TEXT(A8,"mmm-yy") -> Feb-24 | C8: =MONTH(A8) -> 2 | D8: Sales | E8: Payroll | F8: 12000 | G8: 12200 | H8: Internal Payroll | I8: Fixed
A9: 45323 | B9: =TEXT(A9,"mmm-yy") -> Feb-24 | C9: =MONTH(A9) -> 2 | D9: Marketing | E9: Marketing Spend | F9: 8500 | G9: 8700 | H9: Google Ads | I9: Variable
A10: 45323 | B10: =TEXT(A10,"mmm-yy") -> Feb-24 | C10: =MONTH(A10) -> 2 | D10: Product | E10: Cloud Hosting | F10: 4700 | G10: 5350 | H10: AWS | I10: Variable
A11: 45323 | B11: =TEXT(A11,"mmm-yy") -> Feb-24 | C11: =MONTH(A11) -> 2 | D11: Customer Support | E11: Customer Support Tools | F11: 2500 | G11: 2550 | H11: Zendesk | I11: Fixed
A12: 45323 | B12: =TEXT(A12,"mmm-yy") -> Feb-24 | C12: =MONTH(A12) -> 2 | D12: Operations | E12: Software | F12: 3000 | G12: 3200 | H12: Salesforce | I12: Fixed
A13: 45323 | B13: =TEXT(A13,"mmm-yy") -> Feb-24 | C13: =MONTH(A13) -> 2 | D13: G&A | E13: Rent | F13: 6000 | G13: 6000 | H13: WeWork | I13: Fixed
... A37: 45444 | B37: =TEXT(A37,"mmm-yy") -> Jun-24 | C37: =MONTH(A37) -> 6 | D37: G&A | E37: Professional Fees | F37: 4200 | G37: 4800 | H37: Deloitte | I37: Fixed

Sheet Budget_Data
A1: Month | B1: Month_Label | C1: Month_Number | D1: Budget_Subscription_Revenue | E1: Budget_Transaction_Fee_Revenue | F1: Budget_Premium_Revenue | G1: Budget_Setup_Fee_Revenue | H1: Budget_Total_Revenue | I1: Budget_COGS | J1: Budget_Operating_Expenses | K1: Budget_EBITDA
A2: 45292 | B2: =TEXT(A2,"mmm-yy") -> Jan-24 | C2: =MONTH(A2) -> 1 | D2: 1100 | E2: 1700 | F2: 200 | G2: 1200 | H2: 4200 | I2: 1300 | J2: 36000 | K2: -33100
A3: 45323 | B3: =TEXT(A3,"mmm-yy") -> Feb-24 | C3: =MONTH(A3) -> 2 | D3: 1100 | E3: 1800 | F3: 200 | G3: 0 | H3: 3100 | I3: 1350 | J3: 36700 | K3: -34950
A4: 45352 | B4: =TEXT(A4,"mmm-yy") -> Mar-24 | C4: =MONTH(A4) -> 3 | D4: 1400 | E4: 2100 | F4: 250 | G4: 500 | H4: 4250 | I4: 1500 | J4: 38300 | K4: -35550
A5: 45383 | B5: =TEXT(A5,"mmm-yy") -> Apr-24 | C5: =MONTH(A5) -> 4 | D5: 1900 | E5: 2400 | F5: 400 | G5: 700 | H5: 5400 | I5: 1750 | J5: 40200 | K5: -36550
A6: 45413 | B6: =TEXT(A6,"mmm-yy") -> May-24 | C6: =MONTH(A6) -> 5 | D6: 2200 | E6: 2800 | F6: 450 | G6: 500 | H6: 5950 | I6: 1950 | J6: 41500 | K6: -37500
A7: 45444 | B7: =TEXT(A7,"mmm-yy") -> Jun-24 | C7: =MONTH(A7) -> 6 | D7: 2500 | E7: 3200 | F7: 600 | G7: 700 | H7: 7000 | I7: 2200 | J7: 42100 | K7: -37300

Sheet KPI_Data
A1: Month | B1: Month_Label | C1: Month_Number | D1: Active_Customers | E1: New_Customers | F1: Lost_Customers | G1: Churn_Rate | H1: Average_Revenue_Per_Customer | I1: CAC | J1: Gross_Margin | K1: Net_Revenue_Retention
A2: 45292 | B2: =TEXT(A2,"mmm-yy") -> Jan-24 | C2: =MONTH(A2) -> 1 | D2: 2 | E2: 2 | F2: 0 | G2: 0 | H2: 2093.5 | I2: 4600 | J2: 0.69 | K2: 1
A3: 45323 | B3: =TEXT(A3,"mmm-yy") -> Feb-24 | C3: =MONTH(A3) -> 2 | D3: 2 | E3: 0 | F3: 0 | G3: 0 | H3: 1526 | I3: 0 | J3: 0.68 | K3: 1.02
A4: 45352 | B4: =TEXT(A4,"mmm-yy") -> Mar-24 | C4: =MONTH(A4) -> 3 | D4: 3 | E4: 1 | F4: 0 | G4: 0 | H4: 1452.67 | I4: 10300 | J4: 0.66 | K4: 1.03
A5: 45383 | B5: =TEXT(A5,"mmm-yy") -> Apr-24 | C5: =MONTH(A5) -> 4 | D5: 4 | E5: 1 | F5: 0 | G5: 0 | H5: 1645.75 | I5: 9800 | J5: 0.65 | K5: 1.04
A6: 45413 | B6: =TEXT(A6,"mmm-yy") -> May-24 | C6: =MONTH(A6) -> 5 | D6: 5 | E6: 1 | F6: 0 | G6: 0 | H6: 1456 | I6: 11600 | J6: 0.64 | K6: 1.02
A7: 45444 | B7: =TEXT(A7,"mmm-yy") -> Jun-24 | C7: =MONTH(A7) -> 6 | D7: 5 | E7: 1 | F7: 1 | G7: 0.2 | H7: 1786.2 | I7: 10800 | J7: 0.63 | K7: 0.98

Sheet Scenario_Inputs
A1: Scenario | B1: Customer_Growth_Rate | C1: Churn_Rate | D1: Transaction_Volume_Growth | E1: Pricing_Increase | F1: CAC_Change | G1: Payroll_Inflation | H1: Marketing_Spend_Change
A2: Base Case | B2: 0.08 | C2: 0.04 | D2: 0.1 | E2: 0.03 | F2: 0.05 | G2: 0.04 | H2: 0.07
A3: Upside Case | B3: 0.12 | C3: 0.02 | D3: 0.15 | E3: 0.05 | F3: 0 | G3: 0.03 | H3: 0.1
A4: Downside Case | B4: 0.04 | C4: 0.08 | D4: 0.05 | E4: 0 | F4: 0.12 | G4: 0.06 | H4: 0.03

Sheet Monthly_Summary
A1: Month | B1: Month_Label | C1: Month_Number | D1: Actual_Revenue | E1: Actual_Expenses | F1: Actual_COGS | G1: Gross_Profit | H1: Gross_Margin | I1: EBITDA | J1: EBITDA_Margin | K1: Active_Customers | L1: Churn_Rate | M1: CAC | N1: Net_Revenue_Retention
A2: 45292 | B2: =TEXT(A2,"mmm-yy") -> Jan-24 | C2: =MONTH(A2) -> 1 | D2: =SUMIFS(tblRevenue[Total_Revenue],tblRevenue[Month],A2) -> 4187 | E2: =SUMIFS(tblExpenses[Actual_Expense],tblExpenses[Month],A2) -> 37850 | F2: =D2-G2 -> 1297.97 | G2: =D2*H2 -> 2889.03 | H2: =_xlfn.XLOOKUP(A2,KPI_Data!A:A,KPI_Data!J:J) -> 0.69 | I2: =G2-E2 -> -34960.97 | J2: =I2/D2 -> -8.3498854 | K2: =_xlfn.XLOOKUP(A2,tblKPI[Month],tblKPI[Active_Customers]) -> 2 | L2: =_xlfn.XLOOKUP(A2,tblKPI[Month],tblKPI[Churn_Rate]) -> 0 | M2: =_xlfn.XLOOKUP(A2,tblKPI[Month],tblKPI[CAC]) -> 4600 | N2: =_xlfn.XLOOKUP(A2,tblKPI[Month],tblKPI[Net_Revenue_Retention]) -> 1
A3: 45323 | B3: =TEXT(A3,"mmm-yy") -> Feb-24 | C3: =MONTH(A3) -> 2 | D3: =SUMIFS(tblRevenue[Total_Revenue],tblRevenue[Month],A3) -> 3052 | E3: =SUMIFS(tblExpenses[Actual_Expense],tblExpenses[Month],A3) -> 38000 | F3: =D3-G3 -> 976.64 | G3: =D3*H3 -> 2075.36 | H3: =_xlfn.XLOOKUP(A3,KPI_Data!A:A,KPI_Data!J:J) -> 0.68 | I3: =G3-E3 -> -35924.64 | J3: =I3/D3 -> -11.770852 | K3: =_xlfn.XLOOKUP(A3,tblKPI[Month],tblKPI[Active_Customers]) -> 2 | L3: =_xlfn.XLOOKUP(A3,tblKPI[Month],tblKPI[Churn_Rate]) -> 0 | M3: =_xlfn.XLOOKUP(A3,tblKPI[Month],tblKPI[CAC]) -> 0 | N3: =_xlfn.XLOOKUP(A3,tblKPI[Month],tblKPI[Net_Revenue_Retention]) -> 1.02
A4: 45352 | B4: =TEXT(A4,"mmm-yy") -> Mar-24 | C4: =MONTH(A4) -> 3 | D4: =SUMIFS(tblRevenue[Total_Revenue],tblRevenue[Month],A4) -> 4358 | E4: =SUMIFS(tblExpenses[Actual_Expense],tblExpenses[Month],A4) -> 39250 | F4: =D4-G4 -> 1481.72 | G4: =D4*H4 -> 2876.28 | H4: =_xlfn.XLOOKUP(A4,KPI_Data!A:A,KPI_Data!J:J) -> 0.66 | I4: =G4-E4 -> -36373.72 | J4: =I4/D4 -> -8.346425 | K4: =_xlfn.XLOOKUP(A4,tblKPI[Month],tblKPI[Active_Customers]) -> 3 | L4: =_xlfn.XLOOKUP(A4,tblKPI[Month],tblKPI[Churn_Rate]) -> 0 | M4: =_xlfn.XLOOKUP(A4,tblKPI[Month],tblKPI[CAC]) -> 10300 | N4: =_xlfn.XLOOKUP(A4,tblKPI[Month],tblKPI[Net_Revenue_Retention]) -> 1.03
A5: 45383 | B5: =TEXT(A5,"mmm-yy") -> Apr-24 | C5: =MONTH(A5) -> 4 | D5: =SUMIFS(tblRevenue[Total_Revenue],tblRevenue[Month],A5) -> 6583 | E5: =SUMIFS(tblExpenses[Actual_Expense],tblExpenses[Month],A5) -> 41550 | F5: =D5-G5 -> 2304.05 | G5: =D5*H5 -> 4278.95 | H5: =_xlfn.XLOOKUP(A5,KPI_Data!A:A,KPI_Data!J:J) -> 0.65 | I5: =G5-E5 -> -37271.05 | J5: =I5/D5 -> -5.661712 | K5: =_xlfn.XLOOKUP(A5,tblKPI[Month],tblKPI[Active_Customers]) -> 4 | L5: =_xlfn.XLOOKUP(A5,tblKPI[Month],tblKPI[Churn_Rate]) -> 0 | M5: =_xlfn.XLOOKUP(A5,tblKPI[Month],tblKPI[CAC]) -> 9800 | N5: =_xlfn.XLOOKUP(A5,tblKPI[Month],tblKPI[Net_Revenue_Retention]) -> 1.04
A6: 45413 | B6: =TEXT(A6,"mmm-yy") -> May-24 | C6: =MONTH(A6) -> 5 | D6: =SUMIFS(tblRevenue[Total_Revenue],tblRevenue[Month],A6) -> 7280 | E6: =SUMIFS(tblExpenses[Actual_Expense],tblExpenses[Month],A6) -> 44600 | F6: =D6-G6 -> 2620.8 | G6: =D6*H6 -> 4659.2 | H6: =_xlfn.XLOOKUP(A6,KPI_Data!A:A,KPI_Data!J:J) -> 0.64 | I6: =G6-E6 -> -39940.8 | J6: =I6/D6 -> -5.4863736 | K6: =_xlfn.XLOOKUP(A6,tblKPI[Month],tblKPI[Active_Customers]) -> 5 | L6: =_xlfn.XLOOKUP(A6,tblKPI[Month],tblKPI[Churn_Rate]) -> 0 | M6: =_xlfn.XLOOKUP(A6,tblKPI[Month],tblKPI[CAC]) -> 11600 | N6: =_xlfn.XLOOKUP(A6,tblKPI[Month],tblKPI[Net_Revenue_Retention]) -> 1.02
A7: 45444 | B7: =TEXT(A7,"mmm-yy") -> Jun-24 | C7: =MONTH(A7) -> 6 | D7: =SUMIFS(tblRevenue[Total_Revenue],tblRevenue[Month],A7) -> 9531 | E7: =SUMIFS(tblExpenses[Actual_Expense],tblExpenses[Month],A7) -> 43750 | F7: =D7-G7 -> 3526.47 | G7: =D7*H7 -> 6004.53 | H7: =_xlfn.XLOOKUP(A7,KPI_Data!A:A,KPI_Data!J:J) -> 0.63 | I7: =G7-E7 -> -37745.47 | J7: =I7/D7 -> -3.9602843 | K7: =_xlfn.XLOOKUP(A7,tblKPI[Month],tblKPI[Active_Customers]) -> 5 | L7: =_xlfn.XLOOKUP(A7,tblKPI[Month],tblKPI[Churn_Rate]) -> 0.2 | M7: =_xlfn.XLOOKUP(A7,tblKPI[Month],tblKPI[CAC]) -> 10800 | N7: =_xlfn.XLOOKUP(A7,tblKPI[Month],tblKPI[Net_Revenue_Retention]) -> 0.98

Sheet Budget_vs_Actual
A1: Month | B1: Month_Label | C1: Month_Number | D1: Actual_Revenue | E1: Budget_Revenue | F1: Revenue_Variance | G1: Revenue_Variance_% | H1: Actual_Expenses | I1: Budget_Expenses | J1: Expense_Variance | K1: Expense_Variance_% | L1: Actual_EBITDA | M1: Budget_EBITDA | N1: EBITDA_Variance | O1: EBITDA_Variance_%
A2: 45292 | B2: =TEXT(A2,"mmm-yy") -> Jan-24 | C2: =MONTH(A2) -> 1 | D2: =_xlfn.XLOOKUP(A2,Monthly_Summary!A:A,Monthly_Summary!D:D) -> 4187 | E2: =_xlfn.XLOOKUP(A2,tblBudget[Month],tblBudget[Budget_Total_Revenue]) -> 4200 | F2: =D2-E2 -> -13 | G2: =F2/E2 -> -0.0030952381 | H2: =_xlfn.XLOOKUP(A2,Monthly_Summary!A:A,Monthly_Summary!E:E) -> 37850 | I2: =_xlfn.XLOOKUP(A2,tblBudget[Month],tblBudget[Budget_Operating_Expenses]) -> 36000 | J2: =H2-I2 -> 1850 | K2: =J2/I2 -> 0.051388889 | L2: =_xlfn.XLOOKUP(A2,Monthly_Summary!A:A,Monthly_Summary!I:I) -> -34960.97 | M2: =_xlfn.XLOOKUP(A2,tblBudget[Month],tblBudget[Budget_EBITDA]) -> -33100 | N2: =L2-M2 -> -1860.97 | O2: =N2/ABS(M2) -> -0.056222659
A3: 45323 | B3: =TEXT(A3,"mmm-yy") -> Feb-24 | C3: =MONTH(A3) -> 2 | D3: =_xlfn.XLOOKUP(A3,Monthly_Summary!A:A,Monthly_Summary!D:D) -> 3052 | E3: =_xlfn.XLOOKUP(A3,tblBudget[Month],tblBudget[Budget_Total_Revenue]) -> 3100 | F3: =D3-E3 -> -48 | G3: =F3/E3 -> -0.015483871 | H3: =_xlfn.XLOOKUP(A3,Monthly_Summary!A:A,Monthly_Summary!E:E) -> 38000 | I3: =_xlfn.XLOOKUP(A3,tblBudget[Month],tblBudget[Budget_Operating_Expenses]) -> 36700 | J3: =H3-I3 -> 1300 | K3: =J3/I3 -> 0.035422343 | L3: =_xlfn.XLOOKUP(A3,Monthly_Summary!A:A,Monthly_Summary!I:I) -> -35924.64 | M3: =_xlfn.XLOOKUP(A3,tblBudget[Month],tblBudget[Budget_EBITDA]) -> -34950 | N3: =L3-M3 -> -974.64 | O3: =N3/ABS(M3) -> -0.027886695
A4: 45352 | B4: =TEXT(A4,"mmm-yy") -> Mar-24 | C4: =MONTH(A4) -> 3 | D4: =_xlfn.XLOOKUP(A4,Monthly_Summary!A:A,Monthly_Summary!D:D) -> 4358 | E4: =_xlfn.XLOOKUP(A4,tblBudget[Month],tblBudget[Budget_Total_Revenue]) -> 4250 | F4: =D4-E4 -> 108 | G4: =F4/E4 -> 0.025411765 | H4: =_xlfn.XLOOKUP(A4,Monthly_Summary!A:A,Monthly_Summary!E:E) -> 39250 | I4: =_xlfn.XLOOKUP(A4,tblBudget[Month],tblBudget[Budget_Operating_Expenses]) -> 38300 | J4: =H4-I4 -> 950 | K4: =J4/I4 -> 0.024804178 | L4: =_xlfn.XLOOKUP(A4,Monthly_Summary!A:A,Monthly_Summary!I:I) -> -36373.72 | M4: =_xlfn.XLOOKUP(A4,tblBudget[Month],tblBudget[Budget_EBITDA]) -> -35550 | N4: =L4-M4 -> -823.72 | O4: =N4/ABS(M4) -> -0.023170745
A5: 45383 | B5: =TEXT(A5,"mmm-yy") -> Apr-24 | C5: =MONTH(A5) -> 4 | D5: =_xlfn.XLOOKUP(A5,Monthly_Summary!A:A,Monthly_Summary!D:D) -> 6583 | E5: =_xlfn.XLOOKUP(A5,tblBudget[Month],tblBudget[Budget_Total_Revenue]) -> 5400 | F5: =D5-E5 -> 1183 | G5: =F5/E5 -> 0.21907407 | H5: =_xlfn.XLOOKUP(A5,Monthly_Summary!A:A,Monthly_Summary!E:E) -> 41550 | I5: =_xlfn.XLOOKUP(A5,tblBudget[Month],tblBudget[Budget_Operating_Expenses]) -> 40200 | J5: =H5-I5 -> 1350 | K5: =J5/I5 -> 0.03358209 | L5: =_xlfn.XLOOKUP(A5,Monthly_Summary!A:A,Monthly_Summary!I:I) -> -37271.05 | M5: =_xlfn.XLOOKUP(A5,tblBudget[Month],tblBudget[Budget_EBITDA]) -> -36550 | N5: =L5-M5 -> -721.05 | O5: =N5/ABS(M5) -> -0.01972777
A6: 45413 | B6: =TEXT(A6,"mmm-yy") -> May-24 | C6: =MONTH(A6) -> 5 | D6: =_xlfn.XLOOKUP(A6,Monthly_Summary!A:A,Monthly_Summary!D:D) -> 7280 | E6: =_xlfn.XLOOKUP(A6,tblBudget[Month],tblBudget[Budget_Total_Revenue]) -> 5950 | F6: =D6-E6 -> 1330 | G6: =F6/E6 -> 0.22352941 | H6: =_xlfn.XLOOKUP(A6,Monthly_Summary!A:A,Monthly_Summary!E:E) -> 44600 | I6: =_xlfn.XLOOKUP(A6,tblBudget[Month],tblBudget[Budget_Operating_Expenses]) -> 41500 | J6: =H6-I6 -> 3100 | K6: =J6/I6 -> 0.074698795 | L6: =_xlfn.XLOOKUP(A6,Monthly_Summary!A:A,Monthly_Summary!I:I) -> -39940.8 | M6: =_xlfn.XLOOKUP(A6,tblBudget[Month],tblBudget[Budget_EBITDA]) -> -37500 | N6: =L6-M6 -> -2440.8 | O6: =N6/ABS(M6) -> -0.065088
A7: 45444 | B7: =TEXT(A7,"mmm-yy") -> Jun-24 | C7: =MONTH(A7) -> 6 | D7: =_xlfn.XLOOKUP(A7,Monthly_Summary!A:A,Monthly_Summary!D:D) -> 9531 | E7: =_xlfn.XLOOKUP(A7,tblBudget[Month],tblBudget[Budget_Total_Revenue]) -> 7000 | F7: =D7-E7 -> 2531 | G7: =F7/E7 -> 0.36157143 | H7: =_xlfn.XLOOKUP(A7,Monthly_Summary!A:A,Monthly_Summary!E:E) -> 43750 | I7: =_xlfn.XLOOKUP(A7,tblBudget[Month],tblBudget[Budget_Operating_Expenses]) -> 42100 | J7: =H7-I7 -> 1650 | K7: =J7/I7 -> 0.039192399 | L7: =_xlfn.XLOOKUP(A7,Monthly_Summary!A:A,Monthly_Summary!I:I) -> -37745.47 | M7: =_xlfn.XLOOKUP(A7,tblBudget[Month],tblBudget[Budget_EBITDA]) -> -37300 | N7: =L7-M7 -> -445.47 | O7: =N7/ABS(M7) -> -0.011942895

Sheet P&L_Model
A1: Metric | B1: 45292 | C1: 45323 | D1: 45352 | E1: 45383 | F1: 45413 | G1: 45444
A2: Revenue | B2: =_xlfn.XLOOKUP(B$1,Monthly_Summary!$A:$A,Monthly_Summary!$D:$D) -> 4187 | C2: =_xlfn.XLOOKUP(C$1,Monthly_Summary!$A:$A,Monthly_Summary!$D:$D) -> 3052 | D2: =_xlfn.XLOOKUP(D$1,Monthly_Summary!$A:$A,Monthly_Summary!$D:$D) -> 4358 | E2: =_xlfn.XLOOKUP(E$1,Monthly_Summary!$A:$A,Monthly_Summary!$D:$D) -> 6583 | F2: =_xlfn.XLOOKUP(F$1,Monthly_Summary!$A:$A,Monthly_Summary!$D:$D) -> 7280 | G2: =_xlfn.XLOOKUP(G$1,Monthly_Summary!$A:$A,Monthly_Summary!$D:$D) -> 9531
A3: COGS | B3: =_xlfn.XLOOKUP(B$1,Monthly_Summary!$A:$A,Monthly_Summary!$F:$F) -> 1297.97 | C3: =_xlfn.XLOOKUP(C$1,Monthly_Summary!$A:$A,Monthly_Summary!$F:$F) -> 976.64 | D3: =_xlfn.XLOOKUP(D$1,Monthly_Summary!$A:$A,Monthly_Summary!$F:$F) -> 1481.72 | E3: =_xlfn.XLOOKUP(E$1,Monthly_Summary!$A:$A,Monthly_Summary!$F:$F) -> 2304.05 | F3: =_xlfn.XLOOKUP(F$1,Monthly_Summary!$A:$A,Monthly_Summary!$F:$F) -> 2620.8 | G3: =_xlfn.XLOOKUP(G$1,Monthly_Summary!$A:$A,Monthly_Summary!$F:$F) -> 3526.47
A4: Gross Profit | B4: =B2-B3 -> 2889.03 | C4: =C2-C3 -> 2075.36 | D4: =D2-D3 -> 2876.28 | E4: =E2-E3 -> 4278.95 | F4: =F2-F3 -> 4659.2 | G4: =G2-G3 -> 6004.53
A5: Gross Margin % | B5: =B4/B2 -> 0.69 | C5: =C4/C2 -> 0.68 | D5: =D4/D2 -> 0.66 | E5: =E4/E2 -> 0.65 | F5: =F4/F2 -> 0.64 | G5: =G4/G2 -> 0.63
A6: Operating Expenses | B6: =_xlfn.XLOOKUP(B$1,Monthly_Summary!$A:$A,Monthly_Summary!$E:$E) -> 37850 | C6: =_xlfn.XLOOKUP(C$1,Monthly_Summary!$A:$A,Monthly_Summary!$E:$E) -> 38000 | D6: =_xlfn.XLOOKUP(D$1,Monthly_Summary!$A:$A,Monthly_Summary!$E:$E) -> 39250 | E6: =_xlfn.XLOOKUP(E$1,Monthly_Summary!$A:$A,Monthly_Summary!$E:$E) -> 41550 | F6: =_xlfn.XLOOKUP(F$1,Monthly_Summary!$A:$A,Monthly_Summary!$E:$E) -> 44600 | G6: =_xlfn.XLOOKUP(G$1,Monthly_Summary!$A:$A,Monthly_Summary!$E:$E) -> 43750
A7: EBITDA | B7: =B4-B6 -> -34960.97 | C7: =C4-C6 -> -35924.64 | D7: =D4-D6 -> -36373.72 | E7: =E4-E6 -> -37271.05 | F7: =F4-F6 -> -39940.8 | G7: =G4-G6 -> -37745.47
A8: EBITDA Margin % | B8: =B7/B2 -> -8.3498854 | C8: =C7/C2 -> -11.770852 | D8: =D7/D2 -> -8.346425 | E8: =E7/E2 -> -5.661712 | F8: =F7/F2 -> -5.4863736 | G8: =G7/G2 -> -3.9602843

Sheet Scenario_Analysis
A1: NovaPay Analytics - Scenario Analysis
A3: Scenario | B3: Revenue_Growth | C3: Churn_Rate | D3: CAC_Change | E3: Payroll_Inflation | F3: Forecast_Revenue | G3: Forecast_EBITDA
A4: Base Case | B4: =_xlfn.XLOOKUP(A4,tblScenarios[Scenario],tblScenarios[Customer_Growth_Rate]) -> 0.08 | C4: =_xlfn.XLOOKUP(A4,tblScenarios[Scenario],tblScenarios[Churn_Rate]) -> 0.04 | D4: =_xlfn.XLOOKUP(A4,tblScenarios[Scenario],tblScenarios[CAC_Change]) -> 0.05 | E4: =_xlfn.XLOOKUP(A4,tblScenarios[Scenario],tblScenarios[Payroll_Inflation]) -> 0.04 | F4: =_xlfn.XLOOKUP(DATE(2024,6,1),Monthly_Summary!$A:$A,Monthly_Summary!$D:$D)*(1+B4) -> 10293.48 | G4: =_xlfn.XLOOKUP(DATE(2024,6,1),Monthly_Summary!$A:$A,Monthly_Summary!$I:$I)+((F4-_xlfn.XLOOKUP(DATE(2024,6,1),Monthly_Summary!$A:$A,Monthly_Summary!$D:$D))*65%)-(_xlfn.XLOOKUP(DATE(2024,6,1),Monthly_Summary!$A:$A,Monthly_Summary!$E:$E)*E4) -> -38999.858
A5: Upside Case | B5: =_xlfn.XLOOKUP(A5,tblScenarios[Scenario],tblScenarios[Customer_Growth_Rate]) -> 0.12 | C5: =_xlfn.XLOOKUP(A5,tblScenarios[Scenario],tblScenarios[Churn_Rate]) -> 0.02 | D5: =_xlfn.XLOOKUP(A5,tblScenarios[Scenario],tblScenarios[CAC_Change]) -> 0 | E5: =_xlfn.XLOOKUP(A5,tblScenarios[Scenario],tblScenarios[Payroll_Inflation]) -> 0.03 | F5: =_xlfn.XLOOKUP(DATE(2024,6,1),Monthly_Summary!$A:$A,Monthly_Summary!$D:$D)*(1+B5) -> 10674.72 | G5: =_xlfn.XLOOKUP(DATE(2024,6,1),Monthly_Summary!$A:$A,Monthly_Summary!$I:$I)+((F5-_xlfn.XLOOKUP(DATE(2024,6,1),Monthly_Summary!$A:$A,Monthly_Summary!$D:$D))*65%)-(_xlfn.XLOOKUP(DATE(2024,6,1),Monthly_Summary!$A:$A,Monthly_Summary!$E:$E)*E5) -> -38314.552
A6: Downside Case | B6: =_xlfn.XLOOKUP(A6,tblScenarios[Scenario],tblScenarios[Customer_Growth_Rate]) -> 0.04 | C6: =_xlfn.XLOOKUP(A6,tblScenarios[Scenario],tblScenarios[Churn_Rate]) -> 0.08 | D6: =_xlfn.XLOOKUP(A6,tblScenarios[Scenario],tblScenarios[CAC_Change]) -> 0.12 | E6: =_xlfn.XLOOKUP(A6,tblScenarios[Scenario],tblScenarios[Payroll_Inflation]) -> 0.06 | F6: =_xlfn.XLOOKUP(DATE(2024,6,1),Monthly_Summary!$A:$A,Monthly_Summary!$D:$D)*(1+B6) -> 9912.24 | G6: =_xlfn.XLOOKUP(DATE(2024,6,1),Monthly_Summary!$A:$A,Monthly_Summary!$I:$I)+((F6-_xlfn.XLOOKUP(DATE(2024,6,1),Monthly_Summary!$A:$A,Monthly_Summary!$D:$D))*65%)-(_xlfn.XLOOKUP(DATE(2024,6,1),Monthly_Summary!$A:$A,Monthly_Summary!$E:$E)*E6) -> -40122.664
A9: Scenario Interpretation
A10: Base Case: | B10: Revenue improves under normal growth assumptions, but EBITDA remains dependent on expense discipline.
A11: Upside Case: | B11: Higher customer growth and lower churn improve the path toward profitability.
A12: Downside Case: | B12: Higher churn, higher CAC, and payroll inflation create additional pressure on EBITDA and cash runway.

Sheet CFO_Summary
A1: NovaPay Analytics - CFO Summary
A3: Latest Month: | B3: =TEXT(DATE(2024,6,1),"mmm-yy") -> Jun-24
A5: Key Metrics | D5: Scenario Summary
A6: Total Revenue | B6: =_xlfn.XLOOKUP(DATE(2024,6,1),Monthly_Summary!$A:$A,Monthly_Summary!$D:$D) -> 9531 | D6: Base Case Forecast Revenue | E6: =_xlfn.XLOOKUP("Base Case",Scenario_Analysis!$A:$A,Scenario_Analysis!$F:$F) -> 10293.48
A7: Gross Margin | B7: =_xlfn.XLOOKUP(DATE(2024,6,1),Monthly_Summary!$A:$A,Monthly_Summary!$H:$H) -> 0.63 | D7: Upside Case Forecast Revenue | E7: =_xlfn.XLOOKUP("Upside Case",Scenario_Analysis!$A:$A,Scenario_Analysis!$F:$F) -> 10674.72
A8: Operating Expenses | B8: =_xlfn.XLOOKUP(DATE(2024,6,1),Monthly_Summary!$A:$A,Monthly_Summary!$E:$E) -> 43750 | D8: Downside Case Forecast Revenue | E8: =_xlfn.XLOOKUP("Downside Case",Scenario_Analysis!$A:$A,Scenario_Analysis!$F:$F) -> 9912.24
A9: EBITDA | B9: =_xlfn.XLOOKUP(DATE(2024,6,1),Monthly_Summary!$A:$A,Monthly_Summary!$I:$I) -> -37745.47
A10: EBITDA Margin | B10: =_xlfn.XLOOKUP(DATE(2024,6,1),Monthly_Summary!$A:$A,Monthly_Summary!$J:$J) -> -3.9602843
A11: Active Customers | B11: =_xlfn.XLOOKUP(DATE(2024,6,1),Monthly_Summary!$A:$A,Monthly_Summary!$K:$K) -> 5
A12: Churn Rate | B12: =_xlfn.XLOOKUP(DATE(2024,6,1),Monthly_Summary!$A:$A,Monthly_Summary!$L:$L) -> 0.2
A13: CAC | B13: =_xlfn.XLOOKUP(DATE(2024,6,1),Monthly_Summary!$A:$A,Monthly_Summary!$M:$M) -> 10800
A16: Key Insights
A17: 1. Revenue is growing, but profitability remains negative due to high operating expenses.
A18: 2. Marketing spend and cloud hosting are major cost pressure areas.
A19: 3. Churn increased in June, creating risk for recurring revenue quality.
A20: 4. Scenario planning shows profitability depends on customer growth, CAC control, and expense discipline.
A23: Recommended Actions
A24: 1. Reduce high-variance marketing spend and track campaign-level ROI.
A25: 2. Monitor churn by customer segment and create retention actions for at-risk customers.
A26: 3. Improve conversion from Basic to Premium plan to increase recurring revenue quality.
A27: 4. Control cloud hosting costs as transaction volume grows.
